minimist/__init__.py
minimist/example.py
minimist-0.0.2.dist-info/LICENSE
minimist-0.0.2.dist-info/METADATA
minimist-0.0.2.dist-info/WHEEL
minimist-0.0.2.dist-info/top_level.txt
minimist-0.0.2.dist-info/RECORD
