Metadata-Version: 2.1
Name: minimist
Version: 0.0.2
Summary: python minimist
License: MIT
License-File: LICENSE
